ratelimit_requests_cache-2023.10.30.dist-info/METADATA
ratelimit_requests_cache-2023.10.30.dist-info/WHEEL
ratelimit_requests_cache-2023.10.30.dist-info/licenses/LICENSE
ratelimit_requests_cache.py
ratelimit_requests_cache-2023.10.30.dist-info/RECORD
