Metadata-Version: 2.1
Name: ratelimit_requests_cache
Version: 2023.10.30
Summary: Ratelimit Python requests, but only if they're not served from the cache
Author-Email: Bart Broere <mail@bartbroere.eu>
License: MIT
Requires-Python: >=3.8
Requires-Dist: requests_cache
Requires-Dist: ratelimit
